{
    "tw": {
        "Bsc": {
            "caller": "0x200AEe9ba7040d778922A763CE8A50948d61AFF5",
            "tokens":
                [
                    {
                        "token":"0x200AEe9ba7040d778922A763CE8A50948d61AFF5",
                        "fromChainFee": {"whitelist": true, "rate": "0.001"},
                        "toChainFee": [{"toChain": "Polygon","whitelist": false, "rate": "0"},{"toChain": "Eth","whitelist": false, "rate": "0"}]
                    }
                ]
        },
        "Polygon": {
            "caller": "0x200AEe9ba7040d778922A763CE8A50948d61AFF5",
            "tokens":
                [
                    {
                        "token":"0x200AEe9ba7040d778922A763CE8A50948d61AFF5",
                        "toChainFee": [{"toChain": "Bsc","whitelist": false, "rate": "0"},{"toChain": "Eth","whitelist": false, "rate": "0"}]
                    }
                ]
        },
        "Eth": {
            "caller": "0x200AEe9ba7040d778922A763CE8A50948d61AFF5",
            "tokens":
                [
                    {
                       "token":"0x200AEe9ba7040d778922A763CE8A50948d61AFF5", 
                       "fromChainFee": {"whitelist": true, "rate": "0"}
                    }
                ]
        }
    }
}


